kineticforms/__init__.py
kineticforms/db.py
kineticforms-0.0.14.dist-info/METADATA
kineticforms-0.0.14.dist-info/WHEEL
kineticforms-0.0.14.dist-info/top_level.txt
kineticforms-0.0.14.dist-info/RECORD
